CrazyDG/__init__.py
CrazyDG/main_example.py
CrazyDG/_base/__init__.py
CrazyDG/_base/_controller_base/__init__.py
CrazyDG/_base/_controller_base/constants.py
CrazyDG/_base/_controller_base/integral_loop.py
CrazyDG/_base/_controller_base/optimus_prime.py
CrazyDG/_base/_navigation_base/__init__.py
CrazyDG/_base/_navigation_base/imu.py
CrazyDG/_base/_navigation_base/imu_setup.py
CrazyDG/_base/_navigation_base/qualisys.py
CrazyDG/control/__init__.py
CrazyDG/control/backup.py
CrazyDG/crazy/__init__.py
CrazyDG/guidance/__init__.py
CrazyDG/guidance/utils/__init__.py
CrazyDG/guidance/utils/_goto.py
CrazyDG/guidance/utils/_hover.py
CrazyDG/guidance/utils/_landing.py
CrazyDG/guidance/utils/_landing_supporter.py
CrazyDG/guidance/utils/_takeoff.py
CrazyDG/guidance/utils/constants.py
CrazyDG/guidance/utils/smoother.py
CrazyDG/navigation/__init__.py
CrazyDG/recorder/__init__.py
CrazyDG/recorder/recorder.py
CrazyDG/recorder/recorder_backup.py
CrazyDG/recorder/visualizer.py
CrazyDG/recorder/visualizer_backup.py
CrazyDG/swarm/__init__.py
CrazyDG/swarm/swarm_handler.py
CrazyDG/swarm/_swarm_controller/__init__.py
CrazyDG/swarm/_swarm_navigation/__init__.py
CrazyDG-6.1.0.dist-info/METADATA
CrazyDG-6.1.0.dist-info/WHEEL
CrazyDG-6.1.0.dist-info/top_level.txt
CrazyDG-6.1.0.dist-info/RECORD
