Metadata-Version: 2.1
Name: CrazyDG
Version: 6.1.0
Summary: CrazyDG is for convenience
Home-page: https://github.com/Daegeun02/CrazyDG.git
Author: Daegeun02
Author-email: redhawkdg02@gmail.com
License: UNKNOWN
Keywords: CrazyDG,by daegeun,for convenience
Platform: UNKNOWN
Classifier: Programming Language :: Python :: 3.7
Classifier: Programming Language :: Python :: 3.8
Classifier: Programming Language :: Python :: 3.9
Classifier: Programming Language :: Python :: 3.10
Requires-Python: >=3.7
